{
	"answer" : [
		"000袁0塔那那利佛",
		"0齐天大圣00一0手",
		"0达0头0夜夜夜夜0",
		"河内000深00半径",
		"西0陌0浮沉00歌0",
		"走为上0士00莫声谷",
		"廊0桑坦德竞技000",
		"0微0桑0选0小白菜",
		"兰博基尼0州00岩0",
		"000亚0长歌吟松风"],
	"tip" :	{
		"h" : {
			"1-6":	"马达加斯加的首都",
			"2-2":	"小说《西游记》中孙悟空的自称",
			"3-6":	"齐秦演唱的歌曲",
			"4-1":	"越南的首都",
			"4-9":	"连接圆心和圆上任意一点的线段",
			"5-5":	"张嘉译、白百何主演的电视连续剧",
			"6-1":	"兵法三十六计之一",
			"6-8":	"金庸小说《倚天屠龙记》中的人物，武当七侠之一",
			"7-3":	"西班牙足球俱乐部之一",
			"8-8":	"河北民歌，讲述了一个失去母亲的小女孩的悲惨生活",
			"9-1":	"意大利名车品牌",
			"10-6":	"唐代李白的一句诗，下半句为“曲尽河星稀”"
		},

		"v" : {
			"4-1":	"甘肃省西北部的狭长高平地",
			"2-2":	"法国著名足球运动员",
			"8-2":	"互联网上的一种平台，用户可发布简短文字及图片进行交流",
			"5-3":	"汉代的一首乐府诗",
			"1-4":	"民国时发行的一种银元的俗称",
			"7-4":	"非洲中东部的一个国家",
			"5-5":	"一部以德国民间传说为题材的长篇诗剧",
			"3-6":	"京剧曲牌",
			"7-6":	"马克·吐温创作的一篇政治讽刺小说",
			"1-8":	"谢军演唱的歌曲",
			"3-9":	"黄磊、徐熙媛、何润东等主演的一部电视连续剧",
			"8-9":	"央视知名男主持人",
			"1-10":	"又名“九爪木”“五指橘”的一种水果"
		}
	}
}